{
  "version": "6.3.1",
  "flags": {},
  "shapes": [
    {
      "label": "book_spine",
      "points": [
        [
          1508.9795918367347,
          98.16326530612248
        ],
        [
          1600.816326530612,
          94.08163265306128
        ],
        [
          1498.7755102040815,
          1077.7551020408164
        ],
        [
          1423.265306122449,
          1080.0
        ]
      ],
      "group_id": null,
      "description": "",
      "shape_type": "polygon",
      "flags": {},
      "mask": null
    },
    {
      "label": "book_spine",
      "points": [
        [
          1372.2448979591836,
          102.24489795918372
        ],
        [
          1402.8571428571427,
          100.20408163265311
        ],
        [
          1341.6326530612243,
          998.1632653061225
        ],
        [
          1308.9795918367347,
          1000.2040816326531
        ]
      ],
      "group_id": null,
      "description": "",
      "shape_type": "polygon",
      "flags": {},
      "mask": null
    },
    {
      "label": "book_spine",
      "points": [
        [
          1313.061224489796,
          94.08163265306128
        ],
        [
          1376.3265306122448,
          98.16326530612248
        ],
        [
          1302.857142857143,
          1016.530612244898
        ],
        [
          1255.9183673469388,
          1020.6122448979592
        ]
      ],
      "group_id": null,
      "description": "",
      "shape_type": "polygon",
      "flags": {},
      "mask": null
    },
    {
      "label": "book_spine",
      "points": [
        [
          1268.1632653061224,
          118.57142857142863
        ],
        [
          1304.8979591836735,
          116.530612244898
        ],
        [
          1251.8367346938774,
          1024.6938775510205
        ],
        [
          1211.0204081632653,
          1024.6938775510205
        ]
      ],
      "group_id": null,
      "description": "",
      "shape_type": "polygon",
      "flags": {},
      "mask": null
    },
    {
      "label": "book_spine",
      "points": [
        [
          1219.1836734693877,
          41.020408163265344
        ],
        [
          1282.4489795918366,
          38.97959183673474
        ],
        [
          1215.1020408163265,
          1051.2244897959183
        ],
        [
          1176.3265306122448,
          1047.1428571428573
        ]
      ],
      "group_id": null,
      "description": "",
      "shape_type": "polygon",
      "flags": {},
      "mask": null
    },
    {
      "label": "book_spine",
      "points": [
        [
          1147.7551020408162,
          34.89795918367351
        ],
        [
          1215.1020408163265,
          30.8163265306123
        ],
        [
          1174.2857142857142,
          1065.5102040816328
        ],
        [
          1113.061224489796,
          1061.4285714285713
        ]
      ],
      "group_id": null,
      "description": "",
      "shape_type": "polygon",
      "flags": {},
      "mask": null
    },
    {
      "label": "book_spine",
      "points": [
        [
          1094.6938775510203,
          106.32653061224495
        ],
        [
          1141.6326530612243,
          108.36734693877555
        ],
        [
          1117.142857142857,
          1069.5918367346937
        ],
        [
          1074.2857142857142,
          1067.5510204081631
        ]
      ],
      "group_id": null,
      "description": "",
      "shape_type": "polygon",
      "flags": {},
      "mask": null
    },
    {
      "label": "book_spine",
      "points": [
        [
          1041.6326530612243,
          69.59183673469393
        ],
        [
          1090.612244897959,
          65.5102040816327
        ],
        [
          1078.3673469387754,
          1071.6326530612243
        ],
        [
          1033.469387755102,
          1080.0
        ]
      ],
      "group_id": null,
      "description": "",
      "shape_type": "polygon",
      "flags": {},
      "mask": null
    },
    {
      "label": "book_spine",
      "points": [
        [
          953.8775510204082,
          263.4693877551021
        ],
        [
          1033.469387755102,
          261.4285714285715
        ],
        [
          1027.3469387755101,
          1077.7551020408164
        ],
        [
          955.9183673469388,
          1077.7551020408164
        ]
      ],
      "group_id": null,
      "description": "",
      "shape_type": "polygon",
      "flags": {},
      "mask": null
    },
    {
      "label": "book_spine",
      "points": [
        [
          892.6530612244898,
          36.93877551020414
        ],
        [
          941.6326530612245,
          41.020408163265344
        ],
        [
          957.9591836734694,
          1079.795918367347
        ],
        [
          902.8571428571429,
          1077.7551020408164
        ]
      ],
      "group_id": null,
      "description": "",
      "shape_type": "polygon",
      "flags": {},
      "mask": null
    },
    {
      "label": "book_spine",
      "points": [
        [
          843.6734693877552,
          69.59183673469393
        ],
        [
          880.4081632653061,
          67.55102040816332
        ],
        [
          906.9387755102041,
          1075.7142857142858
        ],
        [
          862.0408163265306,
          1077.7551020408164
        ]
      ],
      "group_id": null,
      "description": "",
      "shape_type": "polygon",
      "flags": {},
      "mask": null
    },
    {
      "label": "book_spine",
      "points": [
        [
          790.6122448979592,
          124.69387755102046
        ],
        [
          839.5918367346939,
          118.57142857142863
        ],
        [
          857.9591836734694,
          1075.7142857142858
        ],
        [
          808.9795918367347,
          1077.7551020408164
        ]
      ],
      "group_id": null,
      "description": "",
      "shape_type": "polygon",
      "flags": {},
      "mask": null
    },
    {
      "label": "book_spine",
      "points": [
        [
          690.6122448979592,
          32.857142857142904
        ],
        [
          776.3265306122449,
          30.8163265306123
        ],
        [
          802.8571428571429,
          1075.7142857142858
        ],
        [
          733.469387755102,
          1075.7142857142858
        ]
      ],
      "group_id": null,
      "description": "",
      "shape_type": "polygon",
      "flags": {},
      "mask": null
    },
    {
      "label": "book_spine",
      "points": [
        [
          629.3877551020408,
          177.75510204081638
        ],
        [
          692.6530612244898,
          173.67346938775518
        ],
        [
          731.4285714285714,
          1075.7142857142858
        ],
        [
          676.3265306122449,
          1073.6734693877552
        ]
      ],
      "group_id": null,
      "description": "",
      "shape_type": "polygon",
      "flags": {},
      "mask": null
    },
    {
      "label": "book_spine",
      "points": [
        [
          562.0408163265306,
          181.8367346938776
        ],
        [
          625.3061224489796,
          185.91836734693885
        ],
        [
          672.2448979591837,
          1075.7142857142858
        ],
        [
          615.1020408163265,
          1073.6734693877552
        ]
      ],
      "group_id": null,
      "description": "",
      "shape_type": "polygon",
      "flags": {},
      "mask": null
    },
    {
      "label": "book_spine",
      "points": [
        [
          488.5714285714285,
          281.8367346938776
        ],
        [
          555.9183673469388,
          277.7551020408164
        ],
        [
          608.9795918367347,
          1075.7142857142858
        ],
        [
          543.6734693877551,
          1079.795918367347
        ]
      ],
      "group_id": null,
      "description": "",
      "shape_type": "polygon",
      "flags": {},
      "mask": null
    },
    {
      "label": "book_spine",
      "points": [
        [
          447.75510204081627,
          316.530612244898
        ],
        [
          484.4897959183673,
          312.4489795918368
        ],
        [
          541.6326530612245,
          1077.7551020408164
        ],
        [
          506.93877551020404,
          1077.7551020408164
        ]
      ],
      "group_id": null,
      "description": "",
      "shape_type": "polygon",
      "flags": {},
      "mask": null
    },
    {
      "label": "book_spine",
      "points": [
        [
          376.3265306122448,
          165.5102040816327
        ],
        [
          443.67346938775506,
          161.4285714285715
        ],
        [
          500.81632653061223,
          1080.0
        ],
        [
          445.71428571428567,
          1080.0
        ]
      ],
      "group_id": null,
      "description": "",
      "shape_type": "polygon",
      "flags": {},
      "mask": null
    },
    {
      "label": "book_spine",
      "points": [
        [
          323.2653061224489,
          285.91836734693885
        ],
        [
          386.5306122448979,
          281.8367346938776
        ],
        [
          445.71428571428567,
          1077.7551020408164
        ],
        [
          394.69387755102036,
          1080.0
        ]
      ],
      "group_id": null,
      "description": "",
      "shape_type": "polygon",
      "flags": {},
      "mask": null
    },
    {
      "label": "book_spine",
      "points": [
        [
          215.10204081632648,
          128.77551020408168
        ],
        [
          282.4489795918367,
          124.69387755102046
        ],
        [
          386.5306122448979,
          1077.7551020408164
        ],
        [
          315.1020408163265,
          1079.795918367347
        ]
      ],
      "group_id": null,
      "description": "",
      "shape_type": "polygon",
      "flags": {},
      "mask": null
    },
    {
      "label": "book_spine",
      "points": [
        [
          153.8775510204081,
          290.00000000000006
        ],
        [
          227.34693877551015,
          290.00000000000006
        ],
        [
          315.1020408163265,
          1075.7142857142858
        ],
        [
          253.87755102040813,
          1080.0
        ]
      ],
      "group_id": null,
      "description": "",
      "shape_type": "polygon",
      "flags": {},
      "mask": null
    },
    {
      "label": "book_spine",
      "points": [
        [
          35.51020408163261,
          341.02040816326536
        ],
        [
          147.75510204081627,
          330.8163265306123
        ],
        [
          247.75510204081627,
          1073.6734693877552
        ],
        [
          145.71428571428567,
          1073.6734693877552
        ]
      ],
      "group_id": null,
      "description": "",
      "shape_type": "polygon",
      "flags": {},
      "mask": null
    },
    {
      "label": "book_spine",
      "points": [
        [
          21.224489795918323,
          298.1632653061225
        ],
        [
          0.0,
          310.2915451895044
        ],
        [
          2.8571428571428115,
          647.1428571428572
        ],
        [
          66.12244897959178,
          1075.7142857142858
        ],
        [
          141.63265306122443,
          1059.3877551020407
        ]
      ],
      "group_id": null,
      "description": "",
      "shape_type": "polygon",
      "flags": {},
      "mask": null
    }
  ],
  "imagePath": "004_24s.jpg",
  "imageData": null,
  "imageHeight": 1080,
  "imageWidth": 1920
}