{
  "version": "6.3.1",
  "flags": {},
  "shapes": [
    {
      "label": "book_spine",
      "points": [
        [
          1307.0,
          90.0
        ],
        [
          1296.0,
          108.0
        ],
        [
          1283.0,
          94.0
        ],
        [
          1276.0,
          99.0
        ],
        [
          1267.0,
          173.0
        ],
        [
          1237.0,
          989.0
        ],
        [
          1245.0,
          1004.0
        ],
        [
          1280.0,
          1003.0
        ],
        [
          1288.0,
          989.0
        ],
        [
          1323.0,
          134.0
        ],
        [
          1319.0,
          100.0
        ]
      ],
      "group_id": null,
      "description": "score=0.9994",
      "shape_type": "polygon",
      "flags": {},
      "mask": null
    },
    {
      "label": "book_spine",
      "points": [
        [
          1342.0,
          98.0
        ],
        [
          1328.0,
          104.0
        ],
        [
          1291.0,
          892.0
        ],
        [
          1293.0,
          998.0
        ],
        [
          1320.0,
          1004.0
        ],
        [
          1340.0,
          993.0
        ],
        [
          1357.0,
          171.0
        ],
        [
          1352.0,
          111.0
        ]
      ],
      "group_id": null,
      "description": "score=0.9992",
      "shape_type": "polygon",
      "flags": {},
      "mask": null
    },
    {
      "label": "book_spine",
      "points": [
        [
          988.0,
          116.0
        ],
        [
          974.0,
          116.0
        ],
        [
          958.0,
          130.0
        ],
        [
          948.0,
          193.0
        ],
        [
          908.0,
          1010.0
        ],
        [
          918.0,
          1023.0
        ],
        [
          933.0,
          1014.0
        ],
        [
          954.0,
          1017.0
        ],
        [
          963.0,
          968.0
        ],
        [
          997.0,
          128.0
        ]
      ],
      "group_id": null,
      "description": "score=0.9991",
      "shape_type": "polygon",
      "flags": {},
      "mask": null
    },
    {
      "label": "book_spine",
      "points": [
        [
          1645.7142857142856,
          102.24489795918372
        ],
        [
          1648.0,
          194.0
        ],
        [
          1692.0,
          912.0
        ],
        [
          1694.6938775510203,
          987.9591836734695
        ],
        [
          1711.0204081632653,
          987.9591836734695
        ],
        [
          1713.0,
          980.0
        ],
        [
          1722.0,
          988.0
        ],
        [
          1733.469387755102,
          992.0408163265307
        ],
        [
          1723.0,
          575.0
        ],
        [
          1698.7755102040815,
          324.6938775510205
        ],
        [
          1686.5306122448978,
          106.32653061224495
        ]
      ],
      "group_id": null,
      "description": "score=0.9987",
      "shape_type": "polygon",
      "flags": {},
      "mask": null
    },
    {
      "label": "book_spine",
      "points": [
        [
          1274.2857142857142,
          22.653061224489846
        ],
        [
          1233.469387755102,
          22.653061224489846
        ],
        [
          1222.0,
          53.0
        ],
        [
          1183.0,
          994.0
        ],
        [
          1192.0,
          1008.0
        ],
        [
          1226.0,
          1006.0
        ],
        [
          1233.0,
          992.0
        ],
        [
          1270.0,
          85.0
        ]
      ],
      "group_id": null,
      "description": "score=0.9986",
      "shape_type": "polygon",
      "flags": {},
      "mask": null
    },
    {
      "label": "book_spine",
      "points": [
        [
          823.0,
          7.0
        ],
        [
          790.0,
          23.0
        ],
        [
          781.0,
          95.0
        ],
        [
          735.0,
          1015.0
        ],
        [
          747.0,
          1030.0
        ],
        [
          784.0,
          1024.0
        ],
        [
          833.0,
          69.0
        ],
        [
          833.0,
          21.0
        ]
      ],
      "group_id": null,
      "description": "score=0.9981",
      "shape_type": "polygon",
      "flags": {},
      "mask": null
    },
    {
      "label": "book_spine",
      "points": [
        [
          1037.5510204081631,
          96.12244897959188
        ],
        [
          1008.9795918367348,
          92.04081632653065
        ],
        [
          966.0,
          928.0
        ],
        [
          971.0,
          1009.0
        ],
        [
          986.0,
          1001.0
        ],
        [
          995.0,
          1006.0
        ],
        [
          1036.0,
          155.0
        ]
      ],
      "group_id": null,
      "description": "score=0.9981",
      "shape_type": "polygon",
      "flags": {},
      "mask": null
    },
    {
      "label": "book_spine",
      "points": [
        [
          1589.0,
          28.0
        ],
        [
          1578.0,
          42.0
        ],
        [
          1626.0,
          820.0
        ],
        [
          1635.5102040816325,
          996.1224489795919
        ],
        [
          1647.0,
          997.0
        ],
        [
          1670.0,
          1004.0
        ],
        [
          1683.0,
          993.0
        ],
        [
          1686.5306122448978,
          992.0408163265307
        ],
        [
          1643.0,
          119.0
        ],
        [
          1633.469387755102,
          36.93877551020414
        ]
      ],
      "group_id": null,
      "description": "score=0.9978",
      "shape_type": "polygon",
      "flags": {},
      "mask": null
    },
    {
      "label": "book_spine",
      "points": [
        [
          256.0,
          84.0
        ],
        [
          233.0,
          87.0
        ],
        [
          219.1836734693877,
          90.00000000000004
        ],
        [
          190.61224489795913,
          79.795918367347
        ],
        [
          180.0,
          122.0
        ],
        [
          110.0,
          965.0
        ],
        [
          110.0,
          1038.0
        ],
        [
          125.0,
          1050.0
        ],
        [
          195.0,
          1046.0
        ],
        [
          212.0,
          1001.0
        ],
        [
          269.0,
          99.0
        ]
      ],
      "group_id": null,
      "description": "score=0.9978",
      "shape_type": "polygon",
      "flags": {},
      "mask": null
    },
    {
      "label": "book_spine",
      "points": [
        [
          1739.5918367346937,
          38.97959183673474
        ],
        [
          1734.0,
          61.0
        ],
        [
          1759.0,
          493.0
        ],
        [
          1788.5714285714284,
          947.1428571428572
        ],
        [
          1790.612244897959,
          992.0408163265307
        ],
        [
          1861.0,
          993.0
        ],
        [
          1871.0,
          966.0
        ],
        [
          1812.0,
          129.0
        ],
        [
          1804.8979591836735,
          43.061224489795976
        ]
      ],
      "group_id": null,
      "description": "score=0.9976",
      "shape_type": "polygon",
      "flags": {},
      "mask": null
    },
    {
      "label": "book_spine",
      "points": [
        [
          672.8367346938776,
          96.12244897959181
        ],
        [
          649.795918367347,
          114.48979591836742
        ],
        [
          656.8367346938776,
          123.12244897959181
        ],
        [
          648.8367346938776,
          153.1224489795918
        ],
        [
          626.8367346938776,
          625.1224489795918
        ],
        [
          597.8367346938776,
          1026.1224489795918
        ],
        [
          605.8367346938776,
          1036.1224489795918
        ],
        [
          649.795918367347,
          1024.6938775510205
        ],
        [
          649.795918367347,
          1002.2448979591837
        ],
        [
          706.9387755102041,
          100.20408163265311
        ]
      ],
      "group_id": null,
      "description": "score=0.9974",
      "shape_type": "polygon",
      "flags": {},
      "mask": null
    },
    {
      "label": "book_spine",
      "points": [
        [
          160.0,
          93.0
        ],
        [
          119.0,
          98.0
        ],
        [
          112.0,
          109.0
        ],
        [
          42.0,
          944.0
        ],
        [
          41.0,
          1033.0
        ],
        [
          51.0,
          1043.0
        ],
        [
          94.0,
          1033.0
        ],
        [
          102.8571428571428,
          1038.9795918367347
        ],
        [
          172.0,
          221.0
        ],
        [
          176.0,
          107.0
        ]
      ],
      "group_id": null,
      "description": "score=0.9970",
      "shape_type": "polygon",
      "flags": {},
      "mask": null
    },
    {
      "label": "book_spine",
      "points": [
        [
          1115.1020408163265,
          122.65306122448983
        ],
        [
          1112.0,
          156.0
        ],
        [
          1097.0,
          386.0
        ],
        [
          1076.0,
          1002.0
        ],
        [
          1091.0,
          1027.0
        ],
        [
          1106.0,
          1013.0
        ],
        [
          1115.0,
          958.0
        ],
        [
          1149.0,
          125.0
        ]
      ],
      "group_id": null,
      "description": "score=0.9964",
      "shape_type": "polygon",
      "flags": {},
      "mask": null
    },
    {
      "label": "book_spine",
      "points": [
        [
          953.8775510204082,
          87.95918367346944
        ],
        [
          906.9387755102041,
          87.95918367346944
        ],
        [
          901.0,
          127.0
        ],
        [
          857.0,
          1004.0
        ],
        [
          866.0,
          1017.0
        ],
        [
          897.0,
          1014.0
        ],
        [
          904.0,
          1004.0
        ],
        [
          947.0,
          167.0
        ]
      ],
      "group_id": null,
      "description": "score=0.9952",
      "shape_type": "polygon",
      "flags": {},
      "mask": null
    },
    {
      "label": "book_spine",
      "points": [
        [
          619.1836734693877,
          90.00000000000004
        ],
        [
          622.0,
          114.0
        ],
        [
          616.0,
          105.0
        ],
        [
          605.0,
          170.0
        ],
        [
          554.0,
          1015.0
        ],
        [
          563.0,
          1028.0
        ],
        [
          592.0,
          1023.0
        ],
        [
          599.0,
          1011.0
        ],
        [
          651.0,
          104.0
        ]
      ],
      "group_id": null,
      "description": "score=0.9949",
      "shape_type": "polygon",
      "flags": {},
      "mask": null
    },
    {
      "label": "book_spine",
      "points": [
        [
          474.2857142857142,
          0.2040816326531001
        ],
        [
          439.59183673469386,
          2.2448979591837173
        ],
        [
          428.0,
          106.0
        ],
        [
          373.0,
          1028.0
        ],
        [
          387.0,
          1041.0
        ],
        [
          431.0,
          1032.0
        ],
        [
          439.0,
          987.0
        ],
        [
          498.0,
          84.0
        ],
        [
          498.7755102040816,
          6.326530612244937
        ]
      ],
      "group_id": null,
      "description": "score=0.9926",
      "shape_type": "polygon",
      "flags": {},
      "mask": null
    },
    {
      "label": "book_spine",
      "points": [
        [
          529.0,
          73.0
        ],
        [
          508.0,
          85.0
        ],
        [
          499.0,
          139.0
        ],
        [
          444.0,
          981.0
        ],
        [
          446.0,
          1030.0
        ],
        [
          463.0,
          1038.0
        ],
        [
          493.0,
          1026.0
        ],
        [
          548.0,
          209.0
        ],
        [
          549.795918367347,
          83.8775510204082
        ]
      ],
      "group_id": null,
      "description": "score=0.9915",
      "shape_type": "polygon",
      "flags": {},
      "mask": null
    },
    {
      "label": "book_spine",
      "points": [
        [
          1208.0,
          11.0
        ],
        [
          1191.0,
          14.0
        ],
        [
          1168.1632653061224,
          18.571428571428612
        ],
        [
          1157.9591836734694,
          26.734693877551067
        ],
        [
          1154.0,
          77.0
        ],
        [
          1118.0,
          1005.0
        ],
        [
          1129.0,
          1020.0
        ],
        [
          1168.0,
          1018.0
        ],
        [
          1178.0,
          1004.0
        ],
        [
          1216.0,
          150.0
        ],
        [
          1216.0,
          24.0
        ]
      ],
      "group_id": null,
      "description": "score=0.9908",
      "shape_type": "polygon",
      "flags": {},
      "mask": null
    },
    {
      "label": "book_spine",
      "points": [
        [
          1086.5306122448978,
          4.285714285714334
        ],
        [
          1055.9183673469388,
          0.0
        ],
        [
          1043.0,
          79.0
        ],
        [
          1008.0,
          1006.0
        ],
        [
          1024.0,
          1020.0
        ],
        [
          1061.0,
          1018.0
        ],
        [
          1071.0,
          998.0
        ],
        [
          1117.142857142857,
          8.367346938775555
        ]
      ],
      "group_id": null,
      "description": "score=0.9896",
      "shape_type": "polygon",
      "flags": {},
      "mask": null
    },
    {
      "label": "book_spine",
      "points": [
        [
          319.1836734693877,
          69.59183673469393
        ],
        [
          290.61224489795916,
          55.30612244897965
        ],
        [
          277.0,
          101.0
        ],
        [
          217.0,
          928.0
        ],
        [
          215.0,
          1030.0
        ],
        [
          230.0,
          1048.0
        ],
        [
          262.0,
          1038.0
        ],
        [
          326.0,
          211.0
        ],
        [
          337.5510204081632,
          77.75510204081637
        ]
      ],
      "group_id": null,
      "description": "score=0.9878",
      "shape_type": "polygon",
      "flags": {},
      "mask": null
    },
    {
      "label": "book_spine",
      "points": [
        [
          1821.0,
          42.0
        ],
        [
          1813.0,
          50.0
        ],
        [
          1874.0,
          962.0
        ],
        [
          1880.0,
          989.0
        ],
        [
          1906.0,
          992.0
        ],
        [
          1918.0,
          979.0
        ],
        [
          1918.0,
          532.0
        ],
        [
          1899.0,
          123.0
        ],
        [
          1896.7346938775509,
          43.061224489795976
        ]
      ],
      "group_id": null,
      "description": "score=0.9872",
      "shape_type": "polygon",
      "flags": {},
      "mask": null
    },
    {
      "label": "book_spine",
      "points": [
        [
          888.0,
          94.0
        ],
        [
          846.0,
          99.0
        ],
        [
          835.0,
          164.0
        ],
        [
          796.0,
          917.0
        ],
        [
          796.0,
          1011.0
        ],
        [
          803.0,
          1018.0
        ],
        [
          847.0,
          1016.0
        ],
        [
          854.0,
          998.0
        ],
        [
          896.0,
          181.0
        ],
        [
          895.0,
          104.0
        ]
      ],
      "group_id": null,
      "description": "score=0.9860",
      "shape_type": "polygon",
      "flags": {},
      "mask": null
    },
    {
      "label": "book_spine",
      "points": [
        [
          597.0,
          82.0
        ],
        [
          581.0,
          82.0
        ],
        [
          574.0,
          95.0
        ],
        [
          562.0,
          89.0
        ],
        [
          505.0,
          967.0
        ],
        [
          506.0,
          1023.0
        ],
        [
          519.0,
          1029.0
        ],
        [
          543.0,
          1025.0
        ],
        [
          551.0,
          1001.0
        ],
        [
          604.0,
          145.0
        ]
      ],
      "group_id": null,
      "description": "score=0.9719",
      "shape_type": "polygon",
      "flags": {},
      "mask": null
    },
    {
      "label": "book_spine",
      "points": [
        [
          1690.612244897959,
          126.73469387755107
        ],
        [
          1706.938775510204,
          126.73469387755107
        ],
        [
          1766.1224489795918,
          992.0408163265307
        ],
        [
          1731.4285714285713,
          987.9591836734695
        ]
      ],
      "group_id": null,
      "description": "",
      "shape_type": "polygon",
      "flags": {},
      "mask": null
    },
    {
      "label": "book_spine",
      "points": [
        [
          757.9591836734694,
          12.448979591836775
        ],
        [
          778.3673469387755,
          14.489795918367392
        ],
        [
          729.3877551020408,
          1024.6938775510205
        ],
        [
          696.7346938775511,
          1024.6938775510205
        ]
      ],
      "group_id": null,
      "description": "",
      "shape_type": "polygon",
      "flags": {},
      "mask": null
    },
    {
      "label": "book_spine",
      "points": [
        [
          717.1428571428571,
          0.0
        ],
        [
          751.8367346938776,
          6.326530612244937
        ],
        [
          688.5714285714286,
          1022.6530612244898
        ],
        [
          662.0408163265306,
          1022.6530612244898
        ]
      ],
      "group_id": null,
      "description": "",
      "shape_type": "polygon",
      "flags": {},
      "mask": null
    },
    {
      "label": "book_spine",
      "points": [
        [
          388.5714285714285,
          126.73469387755107
        ],
        [
          429.3877551020408,
          126.73469387755107
        ],
        [
          372.2448979591836,
          1036.938775510204
        ],
        [
          323.2653061224489,
          1036.938775510204
        ]
      ],
      "group_id": null,
      "description": "",
      "shape_type": "polygon",
      "flags": {},
      "mask": null
    },
    {
      "label": "book_spine",
      "points": [
        [
          33.46938775510199,
          75.71428571428577
        ],
        [
          106.93877551020404,
          79.795918367347
        ],
        [
          33.46938775510199,
          1053.265306122449
        ],
        [
          0.0,
          1051.5918367346937
        ],
        [
          0.0,
          445.1020408163266
        ]
      ],
      "group_id": null,
      "description": "",
      "shape_type": "polygon",
      "flags": {},
      "mask": null
    },
    {
      "label": "book_spine",
      "points": [
        [
          343.67346938775506,
          69.59183673469393
        ],
        [
          390.61224489795916,
          77.75510204081637
        ],
        [
          319.1836734693877,
          1047.142857142857
        ],
        [
          264.08163265306115,
          1038.9795918367347
        ]
      ],
      "group_id": null,
      "description": "",
      "shape_type": "polygon",
      "flags": {},
      "mask": null
    }
  ],
  "imagePath": "055_30s.jpg",
  "imageData": null,
  "imageHeight": 1080,
  "imageWidth": 1920
}